snregales/__init__.py
snregales/classes/__init__.py
snregales/classes/abstract/__init__.py
snregales/classes/abstract/parser.py
snregales-0.2.0.dist-info/WHEEL
snregales-0.2.0.dist-info/METADATA
snregales-0.2.0.dist-info/RECORD
